__init__.py
ruppell.py
readers/AbstractReader.py
readers/DocxReader.py
readers/ImageReader.py
readers/PdfReader.py
readers/__init__.py
utils/__init__.py
utils/utils.py
ruppell-1.0.1.dist-info/LICENSE
ruppell-1.0.1.dist-info/METADATA
ruppell-1.0.1.dist-info/WHEEL
ruppell-1.0.1.dist-info/top_level.txt
ruppell-1.0.1.dist-info/RECORD
