Metadata-Version: 2.1
Name: ruppell
Version: 1.0.1
Summary: Ruppell is a Python package to help in text extraction from documents.
Home-page: https://github.com/joorgelm/ruppell
Download-URL: https://github.com/joorgelm/ruppell/archive/1.0.1.tar.gz
Author: Jorge Melgarejo
Author-email: melgarejo.colarte@gmail.com
License: MIT License
Keywords: ocr text extractor
License-File: LICENSE
Requires-Dist: Pillow (~=10.0.0)
Requires-Dist: pytesseract (~=0.3.10)
Requires-Dist: setuptools (~=68.0.0)
Requires-Dist: pdfminer.six (==20221105)
Requires-Dist: docx2txt (~=0.8)
Requires-Dist: pandas (~=2.0.3)
